china_stock_mcp/__init__.py
china_stock_mcp/__main__.py
china_stock_mcp/cache_utils.py
china_stock_mcp/server.py
china_stock_mcp-0.1.16.dist-info/WHEEL
china_stock_mcp-0.1.16.dist-info/entry_points.txt
china_stock_mcp-0.1.16.dist-info/METADATA
china_stock_mcp-0.1.16.dist-info/RECORD
