Metadata-Version: 2.3
Name: china-stock-mcp
Version: 0.1.16
Summary: MCP server that provides access to Chinese stock market data using akshare
Keywords: akshare,stock,mcp,mcp-server
Author: postback
Author-email: postback <ssf@foxmail.com>
License: MIT
Requires-Dist: akshare>=1.17.67
Requires-Dist: akshare-one>=0.3.12
Requires-Dist: fastmcp>=2.12.4
Requires-Dist: uvicorn>=0.37.0
Requires-Dist: pyarrow
Requires-Python: >=3.12
Project-URL: Homepage, https://github.com/xinkuang/china-stock-mcp
Project-URL: Repository, https://github.com/xinkuang/china-stock-mcp.git
